Metadata-Version: 2.1
Name: sciutils
Version: 0.8
Summary: UNKNOWN
Home-page: UNKNOWN
License: UNKNOWN
Platform: UNKNOWN
Provides-Extra: tests
Provides-Extra: docs
